datagokr/DataGoKr.py
datagokr/__init__.py
datagokr/scripts.py
datagokr/airkorea/ArpltnInforInqireSvc.py
datagokr/airkorea/__init__.py
datagokr/kma/AsosHourlyInfoService.py
datagokr/kma/VilageFcstInfoService_2_0.py
datagokr/kma/__init__.py
datagokr/kma/info.py
datagokr-2022.1.6.dist-info/LICENSE
datagokr-2022.1.6.dist-info/METADATA
datagokr-2022.1.6.dist-info/WHEEL
datagokr-2022.1.6.dist-info/entry_points.txt
datagokr-2022.1.6.dist-info/top_level.txt
datagokr-2022.1.6.dist-info/RECORD
