Metadata-Version: 2.1
Name: datagokr
Version: 2022.1.6
Summary: Get data from data.go.kr
Home-page: UNKNOWN
Author: Woojin Cho
Author-email: woojin.cho@gmail.com
License: UNKNOWN
Platform: UNKNOWN
License-File: LICENSE
Requires-Dist: click
Requires-Dist: pendulum
Requires-Dist: pydantic
Requires-Dist: requests
Requires-Dist: urllib3
